staze/__init__.py
staze/__main__.py
staze/conftest.py
staze/__pycache__/__init__.cpython-310.pyc
staze/__pycache__/__main__.cpython-310.pyc
staze/__pycache__/conftest.cpython-310-pytest-7.1.2.pyc
staze/assets/logo.png
staze/constants/__pycache__/enums.cpython-310.pyc
staze/constants/__pycache__/hints.cpython-310.pyc
staze/constants/__pycache__/orm_types.cpython-310.pyc
staze/core/error_handler.py
staze/core/filter_query_enum.py
staze/core/log.py
staze/core/login_required_dec.py
staze/core/noconflict.py
staze/core/not_found_error.py
staze/core/query_parameter_error.py
staze/core/__pycache__/error_handler.cpython-310.pyc
staze/core/__pycache__/filter_query_enum.cpython-310.pyc
staze/core/__pycache__/hints.cpython-310.pyc
staze/core/__pycache__/log.cpython-310.pyc
staze/core/__pycache__/login_required_dec.cpython-310.pyc
staze/core/__pycache__/noconflict.cpython-310.pyc
staze/core/__pycache__/not_found_error.cpython-310.pyc
staze/core/__pycache__/query_parameter_error.cpython-310.pyc
staze/core/app/app.py
staze/core/app/app_mode_enum.py
staze/core/app/staze_sv_ie.py
staze/core/app/turbo_action_enum.py
staze/core/app/__pycache__/app.cpython-310.pyc
staze/core/app/__pycache__/app_mode_enum.cpython-310.pyc
staze/core/app/__pycache__/http_method_enum.cpython-310.pyc
staze/core/app/__pycache__/puft.cpython-310.pyc
staze/core/app/__pycache__/puft_sv_ie.cpython-310.pyc
staze/core/app/__pycache__/turbo_action_enum.cpython-310.pyc
staze/core/assembler/assembler.py
staze/core/assembler/assembler_error.py
staze/core/assembler/assembler_test.py
staze/core/assembler/build.py
staze/core/assembler/config_extension_enum.py
staze/core/assembler/__pycache__/assembler.cpython-310.pyc
staze/core/assembler/__pycache__/assembler_error.cpython-310.pyc
staze/core/assembler/__pycache__/assembler_test.cpython-310-pytest-7.1.2.pyc
staze/core/assembler/__pycache__/build.cpython-310.pyc
staze/core/assembler/__pycache__/config_extension_enum.cpython-310.pyc
staze/core/cli/cli.py
staze-0.1.0.dev0.dist-info/METADATA
staze-0.1.0.dev0.dist-info/WHEEL
staze-0.1.0.dev0.dist-info/entry_points.txt
staze-0.1.0.dev0.dist-info/top_level.txt
staze-0.1.0.dev0.dist-info/RECORD
