Metadata-Version: 2.1
Name: staze
Version: 0.1.0.dev0
Summary: Upgraded layer over Flask.
Home-page: https://github.com/ryzhovalex/staze
Author: Alexander Ryzhov
Author-email: thed4rkof@gmail.com
License: MIT
Keywords: flask+,web-framework,flask,flask-template
Classifier: Development Status :: 2 - Pre-Alpha
Classifier: Intended Audience :: Developers
Classifier: Topic :: Software Development :: Build Tools
Classifier: License :: OSI Approved :: MIT License
Classifier: Programming Language :: Python :: 3.10
Requires-Dist: flask
Requires-Dist: warepy (==0.7.1)
Requires-Dist: requests
Requires-Dist: turbo-flask
Requires-Dist: flask-migrate
Requires-Dist: pytest
Requires-Dist: flask-cors
Requires-Dist: flask-session
Requires-Dist: redis
Requires-Dist: click
Requires-Dist: python-dotenv
Requires-Dist: flask-socketio
Requires-Dist: loguru
Requires-Dist: pydantic
